bodo_platform_extensions/__init__.py
bodo_platform_extensions/_version.py
bodo_platform_extensions/adls_setup_magic.py
bodo_platform_extensions/helper.py
bodo_platform_extensions/hostfile_update_magic.py
bodo_platform_extensions/magics_base.py
bodo_platform_extensions/package_installation_magics.py
bodo_platform_extensions/parallel_shell_magic.py
bodo_platform_extensions/platform_utils.py
bodo_platform_extensions/sql_magic.py
bodo_platform_extensions/sql/__init__.py
bodo_platform_extensions/sql/transform.py
tests/__init__.py
tests/conftest.py
tests/test_magics.py
bodo_platform_extensions-1.2.0.dist-info/LICENSE
bodo_platform_extensions-1.2.0.dist-info/METADATA
bodo_platform_extensions-1.2.0.dist-info/WHEEL
bodo_platform_extensions-1.2.0.dist-info/top_level.txt
bodo_platform_extensions-1.2.0.dist-info/RECORD
